{
    "key": "taxonomy_64da67c2d0d61",
    "title": "Guest Xperiences",
    "menu_order": 0,
    "active": true,
    "taxonomy": "guests",
    "object_type": [
        "guest",
        "feature",
        "partner",
        "ticket"
    ],
    "advanced_configuration": 1,
    "import_source": "cptui",
    "import_date": 1692035010,
    "labels": {
        "name": "Guest Xperiences ",
        "singular_name": "Guest Xperience",
        "menu_name": "Guest Xperiences ",
        "all_items": "All Guest Xperiences ",
        "edit_item": "Edit Guest Xperience",
        "view_item": "View Guest Xperience",
        "update_item": "Update Guest Xperience",
        "add_new_item": "Add New Guest Xperience",
        "new_item_name": "New Guest Xperience Name",
        "parent_item": "Parent Guest Xperience",
        "parent_item_colon": "Parent Guest Xperience:",
        "search_items": "Search Guest Xperiences ",
        "most_used": "",
        "not_found": "No guest xperiences  found",
        "no_terms": "No guest xperiences ",
        "name_field_description": "",
        "slug_field_description": "",
        "parent_field_description": "",
        "desc_field_description": "",
        "filter_by_item": "Filter by guest xperience",
        "items_list_navigation": "Guest Xperiences  list navigation",
        "items_list": "Guest Xperiences  list",
        "back_to_items": "← Go to guest xperiences ",
        "item_link": "Guest Xperience Link",
        "item_link_description": "A link to a guest xperience"
    },
    "description": "The Xperiences Guests are involved in at the Convention.",
    "capabilities": {
        "manage_terms": "manage_categories",
        "edit_terms": "manage_categories",
        "delete_terms": "manage_categories",
        "assign_terms": "edit_posts"
    },
    "public": 1,
    "publicly_queryable": 1,
    "hierarchical": 1,
    "show_ui": 1,
    "show_in_menu": 1,
    "show_in_nav_menus": 1,
    "show_in_rest": 1,
    "rest_base": "",
    "rest_namespace": "",
    "rest_controller_class": "",
    "show_tagcloud": 1,
    "show_in_quick_edit": 1,
    "show_admin_column": 1,
    "rewrite": {
        "permalink_rewrite": "custom_permalink",
        "slug": "xperience",
        "with_front": "1",
        "rewrite_hierarchical": "1"
    },
    "query_var": "post_type_key",
    "query_var_name": "",
    "default_term": {
        "default_term_enabled": "0"
    },
    "sort": 1,
    "meta_box": "default",
    "meta_box_cb": "",
    "meta_box_sanitize_cb": "",
    "modified": 1722990323
}
